<!DOCTYPE lensdatabase SYSTEM "lensfun-database.dtd">
<!-- 
DESCRIPTION: 
	Database for all "Canon" branded cameras
	
	See README.md for sorting rules
	This databank is licenced under the Creative Commons Attribution-ShareAlike 3.0 Unported
-->
<lensdatabase version="2">

<!-- Device Name: Canon EF lens mount -->
    <mount>
		<!-- Wikidata Item: Q209633 -->
        <name>Canon EF</name>
        <compat>M42</compat>
        <compat>M39/1</compat>
        <compat>DKL</compat>
        <compat>T2</compat>
        <compat>Tamron Adaptall</compat>
        <compat>Generic</compat>
    </mount>

<!-- Device Name: Canon EF-M lens mount -->
    <mount>
		<!-- Wikidata Item: Q209695 -->
        <name>Canon EF-M</name>
        <compat>Canon EF-S</compat>
        <compat>Canon EF</compat>
        <compat>M42</compat>
        <compat>M39/1</compat>
        <compat>DKL</compat>
        <compat>T2</compat>
        <compat>Generic</compat>
    </mount>
	
<!-- Device Name: Canon EF-S lens mount -->
    <mount>
		<!-- Wikidata Item: Q1155672 -->
        <name>Canon EF-S</name>
        <compat>Canon EF</compat>
        <compat>M42</compat>
        <compat>M39/1</compat>
        <compat>DKL</compat>
        <compat>T2</compat>
        <compat>Tamron Adaptall</compat>
        <compat>Generic</compat>
    </mount>

<!-- Device Name: Canon RF lens mount -->
    <mount>
		<!-- Wikidata Item: Q56487870 -->
        <name>Canon RF</name>
        <compat>Canon EF-S</compat>
        <compat>Canon EF</compat>
        <compat>M42</compat>
        <compat>M39/1</compat>
        <compat>DKL</compat>
        <compat>T2</compat>
        <compat>Generic</compat>
    </mount>
	
<!--
        Canon EF mount
 \/ \/ \/ \/ \/ \/ \/ \/ \/ \/
-->
	
<!-- Device Name: Generic Canon full frame camera with EF lens mount -->
	<camera>
		<!-- Wikidata Item:  -->
        <maker>Canon</maker>
        <model>35mm film: full frame</model>
        <mount>Canon EF</mount>
        <cropfactor>1</cropfactor>
    </camera>
	
<!-- Device Name: Canon EOS-1D -->
	<camera>
		<!-- Wikidata Item: Q63365 -->
        <maker>Canon</maker>
        <model>Canon EOS-1D</model>
        <model lang="en">EOS-1D</model>
        <mount>Canon EF</mount>
        <cropfactor>1.255</cropfactor>
    </camera>
	
<!-- Device Name: Canon EOS-1D Mark II -->
	<camera>
		<!-- Wikidata Item: Q63382 -->
        <maker>Canon</maker>
        <model>Canon EOS-1D Mark II</model>
        <model lang="en">EOS-1D Mark II</model>
        <mount>Canon EF</mount>
        <cropfactor>1.255</cropfactor>
    </camera>
	
<!-- Device Name: Canon EOS-1D Mark II N -->
	<camera>
		<!-- Wikidata Item: Q16534791 -->
        <maker>Canon</maker>
        <model>Canon EOS-1D Mark II N</model>
        <model lang="en">EOS-1D Mark II N</model>
        <mount>Canon EF</mount>
        <cropfactor>1.255</cropfactor>
    </camera>
	
<!-- Device Name: Canon EOS-1D Mark III -->
	<camera>
		<!-- Wikidata Item: Q63580 -->
        <maker>Canon</maker>
        <model>Canon EOS-1D Mark III</model>
        <model lang="en">EOS-1D Mark III</model>
        <mount>Canon EF</mount>
        <cropfactor>1.282</cropfactor>
    </camera>
	
<!-- Device Name: Canon EOS-1D Mark IV -->
	<camera>
		<!-- Wikidata Item: Q63921 -->
        <maker>Canon</maker>
        <model>Canon EOS-1D Mark IV</model>
        <model lang="en">EOS-1D Mark IV</model>
        <mount>Canon EF</mount>
        <cropfactor>1.290</cropfactor>
    </camera>
	
<!-- Device Name: Canon EOS-1Ds -->
	<camera>
		<!-- Wikidata Item: Q63950 -->
        <maker>Canon</maker>
        <model>Canon EOS-1Ds</model>
        <model lang="en">EOS-1Ds</model>
        <mount>Canon EF</mount>
        <cropfactor>1</cropfactor>
    </camera>
	
<!-- Device Name: Canon EOS-1Ds Mark II -->
	<camera>
		<!-- Wikidata Item: Q63978 -->
        <maker>Canon</maker>
        <model>Canon EOS-1Ds Mark II</model>
        <model lang="en">EOS-1Ds Mark II</model>
        <mount>Canon EF</mount>
        <cropfactor>1</cropfactor>
    </camera>
	
<!-- Device Name: Canon EOS-1Ds Mark III -->
	<camera>
		<!-- Wikidata Item: Q63374 -->
        <maker>Canon</maker>
        <model>Canon EOS-1D C</model>
        <model lang="en">EOS-1D C</model>
        <mount>Canon EF</mount>
        <cropfactor>1</cropfactor>
    </camera>
	
<!-- Device Name: Canon EOS-1D C -->
	<camera>
		<!-- Wikidata Item: Q63934 -->
        <maker>Canon</maker>
        <model>Canon EOS-1D X</model>
        <model lang="en">EOS-1D X</model>
        <mount>Canon EF</mount>
        <cropfactor>1</cropfactor>
    </camera>
	
<!-- Device Name: Canon EOS-1D X -->
	<camera>
		<!-- Wikidata Item: Q63934 -->
        <maker>Canon</maker>
        <model>Canon EOS-1D X</model>
        <model lang="en">EOS-1D X</model>
        <mount>Canon EF</mount>
        <cropfactor>1</cropfactor>
    </camera>
	
<!-- Device Name: Canon EOS 1D X Mark II -->
	<camera>
		<!-- Wikidata Item: Q22462514 -->
        <maker>Canon</maker>
        <model>Canon EOS-1D X Mark II</model>
        <model lang="en">EOS-1D X Mark II</model>
        <mount>Canon EF</mount>
        <cropfactor>1</cropfactor>
    </camera>

<!-- Device Name: Canon EOS-1D X Mark III -->
	<camera>
		<!-- Wikidata Item: Q72934580 -->
        <maker>Canon</maker>
        <model>Canon EOS-1D X Mark III</model>
        <model lang="en">EOS-1D X Mark III</model>
        <mount>Canon EF</mount>
        <cropfactor>1</cropfactor>
    </camera>
	
<!-- Device Name: Canon EOS 5D -->
	<camera>
		<!-- Wikidata Item: Q64955 -->
        <maker>Canon</maker>
        <model>Canon EOS 5D</model>
        <model lang="en">EOS 5D</model>
        <mount>Canon EF</mount>
        <cropfactor>1</cropfactor>
    </camera>
	
<!-- Device Name: Canon EOS 5D Mark II -->
	<camera>
		<!-- Wikidata Item: Q64962 -->
        <maker>Canon</maker>
        <model>Canon EOS 5D Mark II</model>
        <model lang="en">EOS 5D Mark II</model>
        <mount>Canon EF</mount>
        <cropfactor>1</cropfactor>
    </camera>
	
<!-- Device Name: Canon EOS 5D Mark III -->
	<camera>
		<!-- Wikidata Item: Q65054 -->
        <maker>Canon</maker>
        <model>Canon EOS 5D Mark III</model>
        <model lang="en">EOS 5D Mark III</model>
        <mount>Canon EF</mount>
        <cropfactor>1</cropfactor>
    </camera>
	
<!-- Device Name: Canon EOS 5D Mark IV -->
	<camera>
		<!-- Wikidata Item: Q26709840 -->
        <maker>Canon</maker>
        <model>Canon EOS 5D Mark IV</model>
        <model lang="en">EOS 5D Mark IV</model>
        <mount>Canon EF</mount>
        <cropfactor>1</cropfactor>
    </camera>

<!-- Device Name: Canon EOS 5Ds -->
	<camera>
		<!-- Wikidata Item: Q18985697 -->
        <maker>Canon</maker>
        <model>Canon EOS 5DS</model>
        <model lang="en">EOS 5DS</model>
        <mount>Canon EF</mount>
        <cropfactor>1</cropfactor>
    </camera>
	
<!-- Device Name: Canon EOS 5DS R -->
	<camera>
		<!-- Wikidata Item: Q20888994 -->
        <maker>Canon</maker>
        <model>Canon EOS 5DS R</model>
        <model lang="en">EOS 5DS R</model>
        <mount>Canon EF</mount>
        <cropfactor>1</cropfactor>
    </camera>
	
<!-- Device Name: Canon EOS 6D -->
	<camera>
		<!-- Wikidata Item: Q66215 -->
        <maker>Canon</maker>
        <model>Canon EOS 6D</model>
        <model lang="en">EOS 6D</model>
        <mount>Canon EF</mount>
        <cropfactor>1.005</cropfactor>
    </camera>
	
<!-- Device Name: Canon EOS 6D Mark II -->
	<camera>
		<!-- Wikidata Item: Q31201954 -->
        <maker>Canon</maker>
        <model>Canon EOS 6D Mark II</model>
        <model lang="en">EOS 6D Mark II</model>
        <mount>Canon EF</mount>
        <cropfactor>1.005</cropfactor>
    </camera>

<!--
 /\ /\ /\ /\ /\ /\ /\ /\ /\ /\
        Canon EF mount
-->

<!--
       Canon EF-M mount
 \/ \/ \/ \/ \/ \/ \/ \/ \/ \/
-->

<!-- Device Name: Canon EOS M -->
	<camera>
		<!-- Wikidata Item: Q63318 -->
        <maker>Canon</maker>
        <model>Canon EOS M</model>
        <model lang="en">EOS M</model>
        <mount>Canon EF-M</mount>
        <cropfactor>1.613</cropfactor>
    </camera>

<!-- Device Name: Canon EOS M2 -->
	<camera>
		<!-- Wikidata Item: Q17048942 -->
        <maker>Canon</maker>
        <model>Canon EOS M2</model>
        <model lang="en">EOS M2</model>
        <mount>Canon EF-M</mount>
        <cropfactor>1.613</cropfactor>
    </camera>

<!-- Device Name: Canon EOS M3 -->
	<camera>
		<!-- Wikidata Item: Q19003041 -->
        <maker>Canon</maker>
        <model>Canon EOS M3</model>
        <model lang="en">EOS M3</model>
        <mount>Canon EF-M</mount>
        <cropfactor>1.613</cropfactor>
    </camera>

<!-- Device Name: Canon EOS M5 -->
	<camera>
		<!-- Wikidata Item: Q26900407 -->
        <maker>Canon</maker>
        <model>Canon EOS M5</model>
        <model lang="en">EOS M5</model>
        <mount>Canon EF-M</mount>
        <cropfactor>1.613</cropfactor>
    </camera>

<!-- Device Name: Canon EOS M6 -->
	<camera>
		<!-- Wikidata Item: Q28796316 -->
        <maker>Canon</maker>
        <model>Canon EOS M6</model>
        <model lang="en">EOS M6</model>
        <mount>Canon EF-M</mount>
        <cropfactor>1.613</cropfactor>
    </camera>

<!-- Device Name: Canon EOS M10 -->
	<camera>
		<!-- Wikidata Item: Q21095935 -->
        <maker>Canon</maker>
        <model>Canon EOS M10</model>
        <model lang="en">EOS M10</model>
        <mount>Canon EF-M</mount>
        <cropfactor>1.613</cropfactor>
    </camera>

<!-- Device Name: Canon EOS M50 -->
	<camera>
		<!-- Wikidata Item: Q51748223 -->
        <maker>Canon</maker>
        <model>Canon EOS M50</model>
        <model lang="en">EOS M50</model>
        <mount>Canon EF-M</mount>
        <cropfactor>1.613</cropfactor>
    </camera>

<!-- Device Name: Canon EOS M100 -->
	<camera>
		<!-- Wikidata Item: Q38148723 -->
        <maker>Canon</maker>
        <model>Canon EOS M100</model>
        <model lang="en">EOS M100</model>
        <mount>Canon EF-M</mount>
        <cropfactor>1.613</cropfactor>
    </camera>
    
<!-- Device Name: Canon EOS M200 -->
	<camera>
		<!-- Wikidata Item: Q68693083 -->
        <maker>Canon</maker>
        <model>Canon EOS M200</model>
        <model lang="en">EOS M200</model>
        <mount>Canon EF-M</mount>
        <cropfactor>1.613</cropfactor>
    </camera>

<!-- Device Name: Canon EOS M50 -->
<!-- Same as Canon EOS M50 (name in Japan) -->
	<camera>
		<!-- Wikidata Item: Q51748223 -->
        <maker>Canon</maker>
        <model>Canon EOS KISS M</model>
        <model lang="en">EOS KISS M</model>
        <mount>Canon EF-M</mount>
        <cropfactor>1.613</cropfactor>
    </camera>

<!--
 /\ /\ /\ /\ /\ /\ /\ /\ /\ /\
       Canon EF-M mount
-->

<!--
       Canon EF-S mount
 \/ \/ \/ \/ \/ \/ \/ \/ \/ \/
-->
	
<!-- Device Name: Canon EOS 7D -->
	<camera>
		<!-- Wikidata Item: Q66219 -->
        <maker>Canon</maker>
        <model>Canon EOS 7D</model>
        <model lang="en">EOS 7D</model>
        <mount>Canon EF-S</mount>
        <cropfactor>1.620</cropfactor>
    </camera
	
<!-- Device Name: Canon EOS 7D Mark II -->
	<camera>
		<!-- Wikidata Item: Q18048758 -->
        <maker>Canon</maker>
        <model>Canon EOS 7D Mark II</model>
        <model lang="en">EOS 7D Mark II</model>
        <mount>Canon EF-S</mount>
        <cropfactor>1.605</cropfactor>
    </camera>
	
<!-- Device Name: Canon EOS 10D -->
	<camera>
		<!-- Wikidata Item: Q63342 -->
        <maker>Canon</maker>
        <model>Canon EOS 10D</model>
        <model lang="en">EOS 10D</model>
        <mount>Canon EF-S</mount>
        <cropfactor>1.587</cropfactor>
    </camera>
	
<!-- Device Name: Canon EOS 20D -->
	<camera>
		<!-- Wikidata Item: Q64029 -->
        <maker>Canon</maker>
        <model>Canon EOS 20D</model>
        <model lang="en">EOS 20D</model>
        <mount>Canon EF-S</mount>
        <cropfactor>1.600</cropfactor>
    </camera>
	
<!-- Device Name: Canon EOS 20Da -->
	<camera>
		<!-- Wikidata Item: Q66512 -->
        <maker>Canon</maker>
        <model>Canon EOS 20D</model>
        <model lang="en">EOS 20D</model>
        <mount>Canon EF-S</mount>
        <cropfactor>1.600</cropfactor>
    </camera>
	
<!-- Device Name: Canon EOS 30D -->
	<camera>
		<!-- Wikidata Item: Q64061 -->
        <maker>Canon</maker>
        <model>Canon EOS 30D</model>
        <model lang="en">EOS 30D</model>
        <mount>Canon EF-S</mount>
        <cropfactor>1.600</cropfactor>
    </camera>
	
<!-- Device Name: Canon EOS 40D -->
	<camera>
		<!-- Wikidata Item: Q64115 -->
        <maker>Canon</maker>
        <model>Canon EOS 40D</model>
        <model lang="en">EOS 40D</model>
        <mount>Canon EF-S</mount>
        <cropfactor>1.622</cropfactor>
    </camera>
	
<!-- Device Name: Canon EOS 50D -->
	<camera>
		<!-- Wikidata Item: Q64475 -->
        <maker>Canon</maker>
        <model>Canon EOS 50D</model>
        <model lang="en">EOS 50D</model>
        <mount>Canon EF-S</mount>
        <cropfactor>1.622</cropfactor>
    </camera>
	
<!-- Device Name: Canon EOS 60D -->
	<camera>
		<!-- Wikidata Item: Q66176 -->
        <maker>Canon</maker>
        <model>Canon EOS 60D</model>
        <model lang="en">EOS 60D</model>
        <mount>Canon EF-S</mount>
        <cropfactor>1.620</cropfactor>
    </camera>
	
<!-- Device Name: Canon EOS 70D -->
	<camera>
		<!-- Wikidata Item: Q13582495 -->
        <maker>Canon</maker>
        <model>Canon EOS 70D</model>
        <model lang="en">EOS 70D</model>
        <mount>Canon EF-S</mount>
        <cropfactor>1.600</cropfactor>
    </camera>
	
<!-- Device Name: Canon EOS 77D -->
	<camera>
		<!-- Wikidata Item: Q28790002 -->
        <maker>Canon</maker>
        <model>Canon EOS 77D</model>
        <model lang="en">EOS 77D</model>
        <mount>Canon EF-S</mount>
        <cropfactor>1.613</cropfactor>
    </camera>
	
<!-- Device Name: Canon EOS 80D -->
	<camera>
		<!-- Wikidata Item: Q22815060 -->
        <maker>Canon</maker>
        <model>Canon EOS 80D</model>
        <model lang="en">EOS 80D</model>
        <mount>Canon EF-S</mount>
        <cropfactor>1.613</cropfactor>
    </camera>
	
<!-- Device Name: Canon EOS 90D -->
	<camera>
		<!-- Wikidata Item: Q67152522 -->
        <maker>Canon</maker>
        <model>Canon EOS 90D</model>
        <model lang="en">EOS 90D</model>
        <mount>Canon EF-S</mount>
        <cropfactor>1.613</cropfactor>
    </camera>
	
<!-- Device Name: Canon EOS 100D -->
	<camera>
		<!-- Wikidata Item: Q7899680 -->
        <maker>Canon</maker>
        <model>Canon EOS 100D</model>
        <model lang="en">EOS 100D</model>
        <mount>Canon EF-S</mount>
        <cropfactor>1.613</cropfactor>
    </camera>
	
<!-- Device Name: Canon EOS 200D -->
	<camera>
		<!-- Wikidata Item: Q31204845 -->
        <maker>Canon</maker>
        <model>Canon EOS 200D</model>
        <model lang="en">EOS 200D</model>
        <mount>Canon EF-S</mount>
        <cropfactor>1.613</cropfactor>
    </camera>
	
<!-- Device Name: Canon EOS 200D Mark II -->
<!-- Same as Canon EOS 250D (name in Australia) -->
	<camera>
		<!-- Wikidata Item: Q63115982 -->
        <maker>Canon</maker>
        <model>Canon EOS 200D Mark II</model>
        <model lang="en">EOS 200D Mark II</model>
        <mount>Canon EF-S</mount>
        <cropfactor>1.613</cropfactor>
    </camera>
	
<!-- Device Name: Canon EOS 250D -->
	<camera>
		<!-- Wikidata Item: Q63115982 -->
        <maker>Canon</maker>
        <model>Canon EOS 250D</model>
        <model lang="en">EOS 250D</model>
        <mount>Canon EF-S</mount>
        <cropfactor>1.613</cropfactor>
    </camera>
	
<!-- Device Name: Canon EOS 300D -->
	<camera>
		<!-- Wikidata Item: Q64039 -->
        <maker>Canon</maker>
        <model>Canon EOS 300D DIGITAL</model>
        <model lang="en">EOS 300D</model>
        <mount>Canon EF-S</mount>
        <cropfactor>1.587</cropfactor>
    </camera>
	
<!-- Device Name: Canon EOS 350D -->
	<camera>
		<!-- Wikidata Item: Q64072 -->
        <maker>Canon</maker>
        <model>Canon EOS 350D DIGITAL</model>
        <model lang="en">EOS 350D</model>
        <mount>Canon EF-S</mount>
        <cropfactor>1.622</cropfactor>
    </camera>
	
<!-- Device Name: Canon EOS 400D -->
	<camera>
		<!-- Wikidata Item: Q64100 -->
        <maker>Canon</maker>
        <model>Canon EOS 400D DIGITAL</model>
        <model lang="en">EOS 400D</model>
        <mount>Canon EF-S</mount>
        <cropfactor>1.622</cropfactor>
    </camera>
	
<!-- Device Name: Canon EOS 450D -->
	<camera>
		<!-- Wikidata Item: Q64126 -->
        <maker>Canon</maker>
        <model>Canon EOS 450D</model>
        <model lang="en">EOS 450D</model>
        <mount>Canon EF-S</mount>
        <cropfactor>1.622</cropfactor>
    </camera>
	
<!-- Device Name: Canon EOS 500D -->
	<camera>
		<!-- Wikidata Item: Q64143 -->
        <maker>Canon</maker>
        <model>Canon EOS 500D</model>
        <model lang="en">EOS 500D</model>
        <mount>Canon EF-S</mount>
        <cropfactor>1.613</cropfactor>
    </camera>
	
<!-- Device Name: Canon EOS 550D -->
	<camera>
		<!-- Wikidata Item: Q64492 -->
        <maker>Canon</maker>
        <model>Canon EOS 550D</model>
        <model lang="en">EOS 550D</model>
        <mount>Canon EF-S</mount>
        <cropfactor>1.613</cropfactor>
    </camera>
	
<!-- Device Name: Canon EOS 600D -->
	<camera>
		<!-- Wikidata Item: Q65663 -->
        <maker>Canon</maker>
        <model>Canon EOS 600D</model>
        <model lang="en">EOS 600D</model>
        <mount>Canon EF-S</mount>
        <cropfactor>1.613</cropfactor>
    </camera>
	
<!-- Device Name: Canon EOS 650D -->
	<camera>
		<!-- Wikidata Item: Q66203 -->
        <maker>Canon</maker>
        <model>Canon EOS 650D</model>
        <model lang="en">EOS 650D</model>
        <mount>Canon EF-S</mount>
        <cropfactor>1.613</cropfactor>
    </camera>
	
<!-- Device Name: Canon EOS 700D -->
	<camera>
		<!-- Wikidata Item: Q7983923 -->
        <maker>Canon</maker>
        <model>Canon EOS 700D</model>
        <model lang="en">EOS 700D</model>
        <mount>Canon EF-S</mount>
        <cropfactor>1.613</cropfactor>
    </camera>
	
<!-- Device Name: Canon EOS 750D -->
	<camera>
		<!-- Wikidata Item: Q19008035 -->
        <maker>Canon</maker>
        <model>Canon EOS 750D</model>
        <model lang="en">EOS 750D</model>
        <mount>Canon EF-S</mount>
        <cropfactor>1.613</cropfactor>
    </camera>
	
<!-- Device Name: Canon EOS 760D -->
	<camera>
		<!-- Wikidata Item: Q19571185 -->
        <maker>Canon</maker>
        <model>Canon EOS 760D</model>
        <model lang="en">EOS 760D</model>
        <mount>Canon EF-S</mount>
        <cropfactor>1.613</cropfactor>
    </camera>
	
<!-- Device Name: Canon EOS 800D -->
	<camera>
		<!-- Wikidata Item: Q28790013 -->
        <maker>Canon</maker>
        <model>Canon EOS 800D</model>
        <model lang="en">EOS 800D</model>
        <mount>Canon EF-S</mount>
        <cropfactor>1.613</cropfactor>
    </camera>
	
<!-- Device Name: Canon EOS 850D -->
	<camera>
		<!-- Wikidata Item: Q93428008 -->
        <maker>Canon</maker>
        <model>Canon EOS 850D</model>
        <model lang="en">EOS 850D</model>
        <mount>Canon EF-S</mount>
        <cropfactor>1.613</cropfactor>
    </camera>
	
<!-- Device Name: Canon EOS 1000D -->
	<camera>
		<!-- Wikidata Item: Q63333 -->
        <maker>Canon</maker>
        <model>Canon EOS 1000D</model>
        <model lang="en">EOS 1000D</model>
        <mount>Canon EF-S</mount>
        <cropfactor>1.622</cropfactor>
    </camera>
	
<!-- Device Name: Canon EOS 1100D -->
	<camera>
		<!-- Wikidata Item: Q63353 -->
        <maker>Canon</maker>
        <model>Canon EOS 1100D</model>
        <model lang="en">EOS 1100D</model>
        <mount>Canon EF-S</mount>
        <cropfactor>1.620</cropfactor>
    </camera>
	
<!-- Device Name: Canon EOS 1200D -->
	<camera>
		<!-- Wikidata Item: Q15728011 -->
        <maker>Canon</maker>
        <model>Canon EOS 1200D</model>
        <model lang="en">EOS 1200D</model>
        <mount>Canon EF-S</mount>
        <cropfactor>1.620</cropfactor>
    </camera>
	
<!-- Device Name: Canon EOS 1300D -->
	<camera>
		<!-- Wikidata Item: Q23702407 -->
        <maker>Canon</maker>
        <model>Canon EOS 1300D</model>
        <model lang="en">EOS 1300D</model>
        <mount>Canon EF-S</mount>
        <cropfactor>1.620</cropfactor>
    </camera>
	
<!-- Device Name: Canon EOS 1500D -->
<!-- Same as Canon EOS 2000D (name in Southeast Asia) -->
	<camera>
		<!-- Wikidata Item: Q52016117 -->
        <maker>Canon</maker>
        <model>Canon EOS 1500D</model>
        <model lang="en">EOS 1500D</model>
        <mount>Canon EF-S</mount>
        <cropfactor>1.613</cropfactor>
    </camera>
	
<!-- Device Name: Canon EOS 2000D -->
	<camera>
		<!-- Wikidata Item: Q52016117 -->
        <maker>Canon</maker>
        <model>Canon EOS 2000D</model>
        <model lang="en">EOS 2000D</model>
        <mount>Canon EF-S</mount>
        <cropfactor>1.613</cropfactor>
    </camera>
	
<!-- Device Name: Canon EOS 3000D -->
<!-- Same as Canon EOS 4000D (name in Southeast Asia) -->
	<camera>
		<!-- Wikidata Item: Q54747245 -->
        <maker>Canon</maker>
        <model>Canon EOS 3000D</model>
        <model lang="en">EOS 3000D</model>
        <mount>Canon EF-S</mount>
        <cropfactor>1.613</cropfactor>
    </camera>
	
<!-- Device Name: Canon EOS 4000D -->
	<camera>
		<!-- Wikidata Item: Q54747245 -->
        <maker>Canon</maker>
        <model>Canon EOS 4000D</model>
        <model lang="en">EOS 4000D</model>
        <mount>Canon EF-S</mount>
        <cropfactor>1.613</cropfactor>
    </camera>
	
<!-- Device Name: Canon EOS 8000D -->
<!-- Same as Canon EOS 760D (name in Japan) -->
	<camera>
		<!-- Wikidata Item: Q19571185 -->
        <maker>Canon</maker>
        <model>Canon EOS 8000D</model>
        <model lang="en"> EOS 8000D</model>
        <mount>Canon EF-S</mount>
        <cropfactor>1.613</cropfactor>
    </camera>
	
<!-- Device Name: Canon EOS 9000D -->
<!-- Same as Canon EOS 8000D (name in Japan) -->
	<camera>
		<!-- Wikidata Item: Q28790002 -->
        <maker>Canon</maker>
        <model>Canon EOS 9000D</model>
        <model lang="en">EOS 9000D</model>
        <mount>Canon EF-S</mount>
        <cropfactor>1.613</cropfactor>
    </camera>
	
<!-- Device Name: Canon EOS D30 -->
	<camera>
		<!-- Wikidata Item: Q66265 -->
        <maker>Canon</maker>
        <model>Canon EOS D30</model>
        <model lang="en">EOS D30</model>
        <mount>Canon EF-S</mount>
        <cropfactor>1.587</cropfactor>
    </camera>
	
<!-- Device Name: Canon EOS D60 -->
	<camera>
		<!-- Wikidata Item: Q66277 -->
        <maker>Canon</maker>
        <model>Canon EOS D60</model>
        <model lang="en">EOS D60</model>
        <mount>Canon EF-S</mount>
        <cropfactor>1.587</cropfactor>
    </camera>
	
<!-- Device Name: Canon EOS D2000 -->
	<camera>
		<!-- Wikidata Item: Q66265 -->
        <maker>Canon</maker>
        <model>EOS D2000</model>
        <mount>Canon EF</mount>
        <cropfactor>1.593</cropfactor>
    </camera>
	
<!-- Device Name: Canon EOS Rebel SL1 -->
<!-- Same as Canon EOS 100D (name in the United States and Canada) -->
	<camera>
		<!-- Wikidata Item: Q7899680 -->
        <maker>Canon</maker>
        <model>Canon EOS REBEL SL1</model>
        <model lang="en">EOS Rebel SL1</model>
        <mount>Canon EF-S</mount>
        <cropfactor>1.613</cropfactor>
    </camera>
	
<!-- Device Name: Canon EOS Rebel SL2 -->
<!-- Same as Canon EOS 200D (name in the United States and Canada) -->
	<camera>
		<!-- Wikidata Item: Q31204845 -->
        <maker>Canon</maker>
        <model>Canon EOS REBEL SL2</model>
        <model lang="en">EOS Rebel SL2</model>
        <mount>Canon EF-S</mount>
        <cropfactor>1.613</cropfactor>
    </camera>
	
<!-- Device Name: Canon EOS Rebel SL3 -->
<!-- Same as Canon EOS 250D (name in the United States and Canada) -->
	<camera>
		<!-- Wikidata Item: Q63115982 -->
        <maker>Canon</maker>
        <model>Canon EOS REBEL SL3</model>
        <model lang="en">EOS Rebel SL3</model>
        <mount>Canon EF-S</mount>
        <cropfactor>1.613</cropfactor>
    </camera>
	
<!-- Device Name: Canon EOS Rebel T1i -->
<!-- Same as Canon EOS 500D (name in the United States and Canada) -->
	<camera>
		<!-- Wikidata Item: Q64143 -->
        <maker>Canon</maker>
        <model>Canon EOS REBEL T1i</model>
        <model lang="en">EOS Rebel T1i</model>
        <mount>Canon EF-S</mount>
        <cropfactor>1.613</cropfactor>
    </camera>
	
<!-- Device Name: Canon EOS Rebel T2i -->
<!-- Same as Canon EOS 550D (name in the United States and Canada) -->
	<camera>
		<!-- Wikidata Item: Q64492 -->
        <maker>Canon</maker>
        <model>Canon EOS REBEL T2i</model>
        <model lang="en">EOS Rebel T2i</model>
        <mount>Canon EF-S</mount>
        <cropfactor>1.613</cropfactor>
    </camera>
	
<!-- Device Name: Canon EOS Rebel T3 -->
<!-- Same as Canon EOS 1100D (name in the United States and Canada) -->
	<camera>
		<!-- Wikidata Item: Q63353 -->
        <maker>Canon</maker>
        <model>Canon EOS REBEL T3</model>
        <model lang="en">EOS Rebel T3</model>
        <mount>Canon EF-S</mount>
        <cropfactor>1.620</cropfactor>
    </camera>
	
<!-- Device Name: Canon EOS Rebel T3i -->
<!-- Same as Canon EOS 600D (name in the United States and Canada) -->
	<camera>
		<!-- Wikidata Item: Q65663 -->
        <maker>Canon</maker>
        <model>Canon EOS REBEL T3i</model>
        <model lang="en">EOS Rebel T3i</model>
        <mount>Canon EF-S</mount>
        <cropfactor>1.613</cropfactor>
    </camera>
	
<!-- Device Name: Canon EOS Rebel T4i -->
<!-- Same as Canon EOS 650D (name in the United States and Canada) -->
	<camera>
		<!-- Wikidata Item: Q66203 -->
        <maker>Canon</maker>
        <model>Canon EOS REBEL T4i</model>
        <model lang="en">EOS Rebel T4i</model>
        <mount>Canon EF-S</mount>
        <cropfactor>1.613</cropfactor>
    </camera>
	
<!-- Device Name: Canon EOS Rebel T5 -->
<!-- Same as Canon EOS 1200D (name in the United States and Canada) -->
	<camera>
		<!-- Wikidata Item: Q15728011 -->
        <maker>Canon</maker>
        <model>Canon EOS REBEL T5</model>
        <model lang="en">EOS Rebel T5</model>
        <mount>Canon EF-S</mount>
        <cropfactor>1.620</cropfactor>
    </camera>
	
<!-- Device Name: Canon EOS Rebel T5i -->
<!-- Same as Canon EOS 700D (name in the United States and Canada) -->
	<camera>
		<!-- Wikidata Item: Q7983923 -->
        <maker>Canon</maker>
        <model>Canon EOS REBEL T5i</model>
        <model lang="en">EOS Rebel T5i</model>
        <mount>Canon EF-S</mount>
        <cropfactor>1.613</cropfactor>
    </camera>
	
<!-- Device Name: Canon EOS Rebel T6 -->
<!-- Same as Canon EOS 1300D (name in the United States and Canada) -->
	<camera>
		<!-- Wikidata Item: Q23702407 -->
        <maker>Canon</maker>
        <model>Canon EOS Rebel T6</model>
        <model lang="en">EOS Rebel T6</model>
        <mount>Canon EF-S</mount>
        <cropfactor>1.620</cropfactor>
    </camera>
	
<!-- Device Name: Canon EOS Rebel T6i -->
<!-- Same as Canon EOS 750D (name in the United States and Canada) -->
	<camera>
		<!-- Wikidata Item: Q19008035 -->
        <maker>Canon</maker>
        <model>Canon EOS Rebel T6i</model>
        <model lang="en">EOS Rebel T6i</model>
        <mount>Canon EF-S</mount>
        <cropfactor>1.613</cropfactor>
    </camera>
	
<!-- Device Name: Canon EOS Rebel T6s -->
<!-- Same as Canon EOS 760D (name in the United States and Canada) -->
	<camera>
		<!-- Wikidata Item: Q19571185 -->
        <maker>Canon</maker>
        <model>Canon EOS Rebel T6s</model>
        <model lang="en">EOS Rebel T6s</model>
        <mount>Canon EF-S</mount>
        <cropfactor>1.613</cropfactor>
    </camera>
	
<!-- Device Name: Canon EOS Rebel T7 -->
<!-- Same as Canon EOS 2000D (name in the United States and Canada) -->
	<camera>
		<!-- Wikidata Item: Q52016117 -->
        <maker>Canon</maker>
        <model>Canon EOS Rebel T7</model>
        <model lang="en">EOS Rebel T7</model>
        <mount>Canon EF-S</mount>
        <cropfactor>1.613</cropfactor>
    </camera>
	
<!-- Device Name: Canon EOS Rebel T7i -->
<!-- Same as Canon EOS 800D (name in the United States and Canada) -->
	<camera>
		<!-- Wikidata Item: Q28790013 -->
        <maker>Canon</maker>
        <model>Canon EOS REBEL T7i</model>
        <model lang="en">EOS Rebel T7i</model>
        <mount>Canon EF-S</mount>
        <cropfactor>1.613</cropfactor>
    </camera>
	
<!-- Device Name: Canon EOS Rebel T8i -->
<!-- Same as Canon EOS 850D (name in the United States and Canada) -->
	<camera>
		<!-- Wikidata Item: Q93428008 -->
        <maker>Canon</maker>
        <model>Canon EOS Rebel T8i</model>
        <model lang="en">EOS Rebel T8i</model>
        <mount>Canon EF-S</mount>
        <cropfactor>1.613</cropfactor>
    </camera>
	
<!-- Device Name: Canon EOS Rebel T100 -->
<!-- Same as Canon EOS 4000D (name in the United States and Canada) -->
	<camera>
		<!-- Wikidata Item: Q54747245 -->
        <maker>Canon</maker>
        <model>Canon EOS Rebel T100</model>
        <model lang="en">EOS Rebel T100</model>
        <mount>Canon EF-S</mount>
        <cropfactor>1.613</cropfactor>
    </camera>
	
<!-- Device Name: Canon EOS Digital Rebel -->
<!-- Same as Canon EOS 300D (name in the United States and Canada) -->
	<camera>
		<!-- Wikidata Item: Q64039 -->
        <maker>Canon</maker>
        <model>Canon EOS DIGITAL REBEL</model>
        <model lang="en">EOS Digital REBEL</model>
        <mount>Canon EF-S</mount>
        <cropfactor>1.587</cropfactor>
    </camera>
	
<!-- Device Name: Canon EOS Rebel XS -->
<!-- Same as Canon EOS 1000D (name in the United States and Canada) -->
	<camera>
		<!-- Wikidata Item: Q63333 -->
        <maker>Canon</maker>
        <model>Canon EOS DIGITAL REBEL XS</model>
        <model lang="en">EOS Digital Rebel XS</model>
        <mount>Canon EF-S</mount>
        <cropfactor>1.622</cropfactor>
    </camera>
	
<!-- Device Name: Canon EOS Rebel XSi -->
<!-- Same as Canon EOS 400D (name in the United States and Canada) -->
	<camera>
		<!-- Wikidata Item: Q64126 -->
        <maker>Canon</maker>
        <model>Canon EOS DIGITAL REBEL XSi</model>
        <model lang="en">EOS Digital Rebel XSi</model>
        <mount>Canon EF-S</mount>
        <cropfactor>1.622</cropfactor>
    </camera>
	
<!-- Device Name: Canon EOS Digital Rebel XT -->
<!-- Same as Canon EOS 350D (name in the United States and Canada) -->
	<camera>
		<!-- Wikidata Item: Q64072 -->
        <maker>Canon</maker>
        <model>Canon EOS DIGITAL REBEL XT</model>
        <model lang="en">EOS Digital Rebel XT</model>
        <mount>Canon EF-S</mount>
        <cropfactor>1.622</cropfactor>
    </camera>
	
<!-- Device Name: Canon EOS Digital Rebel XTi -->
<!-- Same as Canon EOS 400D (name in the United States and Canada) -->
	<camera>
		<!-- Wikidata Item: Q64100 -->
        <maker>Canon</maker>
        <model>Canon EOS DIGITAL REBEL XTi</model>
        <model lang="en">EOS Digital Rebel XTi</model>
        <mount>Canon EF-S</mount>
        <cropfactor>1.622</cropfactor>
    </camera>
	
<!-- Device Name: Canon EOS Kiss Digital -->
<!-- Same as Canon EOS 300D (name in Japan) -->
	<camera>
		<!-- Wikidata Item: Q64039 -->
        <maker>Canon</maker>
        <model>Canon EOS Kiss Digital</model>
        <model lang="en">EOS Kiss Digital</model>
        <mount>Canon EF-S</mount>
        <cropfactor>1.587</cropfactor>
    </camera>
	
<!-- Device Name: Canon EOS Kiss F -->
<!-- Same as Canon EOS 1000D (name in Japan) -->
	<camera>
		<!-- Wikidata Item: Q63333 -->
        <maker>Canon</maker>
        <model>Canon EOS Kiss Digital F</model>
        <model lang="en">EOS Kiss Digital F</model>
        <mount>Canon EF-S</mount>
        <cropfactor>1.622</cropfactor>
    </camera>
	
<!-- Device Name: Canon EOS Kiss Digital N -->
<!-- Same as Canon EOS 350D (name in Japan) -->
	<camera>
		<!-- Wikidata Item: Q64072 -->
        <maker>Canon</maker>
        <model>Canon EOS Kiss Digital N</model>
        <model lang="en">EOS Kiss Digital N</model>
        <mount>Canon EF-S</mount>
        <cropfactor>1.622</cropfactor>
    </camera>
	
<!-- Device Name: Canon EOS Kiss Digital X -->
<!-- Same as Canon EOS 400D (name in Japan) -->
	<camera>
		<!-- Wikidata Item: Q64100 -->
        <maker>Canon</maker>
        <model>Canon EOS Kiss Digital X</model>
        <model lang="en">EOS Kiss Digital X</model>
        <mount>Canon EF-S</mount>
        <cropfactor>1.622</cropfactor>
    </camera>
	
<!-- Device Name: Canon EOS Kiss X2 -->
<!-- Same as Canon EOS 450D (name in Japan) -->
	<camera>
		<!-- Wikidata Item: Q64126 -->
        <maker>Canon</maker>
        <model>Canon EOS Kiss Digital X2</model>
        <model lang="en">EOS Kiss Digital X2</model>
        <mount>Canon EF-S</mount>
        <cropfactor>1.622</cropfactor>
    </camera>
	
<!-- Device Name: Canon EOS Kiss X3 -->
<!-- Same as Canon EOS 500D (name in Japan) -->
	<camera>
		<!-- Wikidata Item: Q64143 -->
        <maker>Canon</maker>
        <model>Canon EOS Kiss X3</model>
        <model lang="en">EOS Kiss X3</model>
        <mount>Canon EF-S</mount>
        <cropfactor>1.613</cropfactor>
    </camera>
	
<!-- Device Name: Canon EOS Kiss X4 -->
<!-- Same as Canon EOS 550D (name in Japan) -->
	<camera>
		<!-- Wikidata Item: Q64492 -->
        <maker>Canon</maker>
        <model>Canon EOS Kiss X4</model>
        <model lang="en">EOS Kiss X4</model>
        <mount>Canon EF-S</mount>
        <cropfactor>1.613</cropfactor>
    </camera>
	
<!-- Device Name: Canon EOS Kiss X5 -->
<!-- Same as Canon EOS 600D (name in Japan) -->
	<camera>
		<!-- Wikidata Item: Q65663 -->
        <maker>Canon</maker>
        <model>Canon EOS Kiss X5</model>
        <model lang="en">EOS Kiss X5</model>
        <mount>Canon EF-S</mount>
        <cropfactor>1.613</cropfactor>
    </camera>
	
<!-- Device Name: Canon EOS Kiss X50 -->
<!-- Same as Canon EOS 1100D (name in Japan) -->
	<camera>
		<!-- Wikidata Item: Q63353 -->
        <maker>Canon</maker>
        <model>Canon EOS Kiss X50</model>
        <model lang="en">EOS Kiss X50</model>
        <mount>Canon EF-S</mount>
        <cropfactor>1.620</cropfactor>
    </camera>
	
<!-- Device Name: Canon EOS Kiss X6i -->
<!-- Same as Canon EOS 650D (name in Japan) -->
	<camera>
		<!-- Wikidata Item: Q66203 -->
        <maker>Canon</maker>
        <model>Canon EOS Kiss X6i</model>
        <model lang="en">EOS Kiss X6i</model>
        <mount>Canon EF-S</mount>
        <cropfactor>1.613</cropfactor>
    </camera>
	
<!-- Device Name: Canon EOS Kiss X7 -->
<!-- Same as Canon EOS 100D (name in Japan) -->
	<camera>
		<!-- Wikidata Item: Q7899680 -->
        <maker>Canon</maker>
        <model>Canon EOS Kiss X7</model>
        <model lang="en">EOS Kiss X7</model>
        <mount>Canon EF-S</mount>
        <cropfactor>1.613</cropfactor>
    </camera>
	
<!-- Device Name: Canon EOS Kiss X7i -->
<!-- Same as Canon EOS 700D (name in Japan) -->
	<camera>
		<!-- Wikidata Item: Q7983923 -->
        <maker>Canon</maker>
        <model>Canon EOS Kiss X7i</model>
        <model lang="en">EOS Kiss X7i</model>
        <mount>Canon EF-S</mount>
        <cropfactor>1.613</cropfactor>
    </camera>
	
<!-- Device Name: Canon EOS Kiss X70 -->
<!-- Same as Canon EOS 1200D (name in Japan) -->
	<camera>
		<!-- Wikidata Item: Q15728011 -->
        <maker>Canon</maker>
        <model>Canon EOS Kiss X70</model>
        <model lang="en">EOS Kiss X70</model>
        <mount>Canon EF-S</mount>
        <cropfactor>1.620</cropfactor>
    </camera>
	
<!-- Device Name: EOS Kiss X8i -->
<!-- Same as Canon EOS 750D (name in Japan) -->
	<camera>
		<!-- Wikidata Item: Q19008035 -->
        <maker>Canon</maker>
        <model>Canon EOS Kiss X8i</model>
        <model lang="en">EOS Kiss X8i</model>
        <mount>Canon EF-S</mount>
        <cropfactor>1.613</cropfactor>
    </camera>
	
<!-- Device Name: Canon EOS Kiss X80 -->
<!-- Same as Canon EOS 1300D (name in Japan) -->
	<camera>
		<!-- Wikidata Item: Q23702407 -->
        <maker>Canon</maker>
        <model>Canon EOS Kiss X80</model>
        <model lang="en">EOS Kiss X80</model>
        <mount>Canon EF-S</mount>
        <cropfactor>1.620</cropfactor>
    </camera>
	
<!-- Device Name: Canon EOS Kiss X9 -->
<!-- Same as Canon EOS 200D (name in Japan) -->
	<camera>
		<!-- Wikidata Item: Q31204845 -->
        <maker>Canon</maker>
        <model>Canon EOS Kiss X9</model>
        <model lang="en">EOS Kiss X9</model>
        <mount>Canon EF-S</mount>
        <cropfactor>1.613</cropfactor>
    </camera>
	
<!-- Device Name: Canon EOS Kiss X9i -->
<!-- Same as Canon EOS 800D (name in Japan) -->
	<camera>
		<!-- Wikidata Item: Q28790013 -->
        <maker>Canon</maker>
        <model>Canon EOS Kiss X9i</model>
        <model lang="en">EOS Kiss X9i</model>
        <mount>Canon EF-S</mount>
        <cropfactor>1.613</cropfactor>
    </camera>
	
<!-- Device Name: Canon EOS Kiss X90 -->
<!-- Same as Canon EOS 2000D (name in Japan) -->
	<camera>
		<!-- Wikidata Item: Q52016117 -->
        <maker>Canon</maker>
        <model>Canon EOS Kiss X90</model>
        <model lang="en">EOS Kiss X90</model>
        <mount>Canon EF-S</mount>
        <cropfactor>1.613</cropfactor>
    </camera>
	
<!-- Device Name: Canon EOS Kiss X10 -->
<!-- Same as Canon EOS 250D (name in Japan) -->
	<camera>
		<!-- Wikidata Item: Q63115982 -->
        <maker>Canon</maker>
        <model>Canon EOS Kiss X10</model>
        <model lang="en">EOS Kiss X10</model>
        <mount>Canon EF-S</mount>
        <cropfactor>1.613</cropfactor>
    </camera>
	
<!-- Device Name: Canon EOS Kiss X10i -->
<!-- Same as Canon EOS 850D (name in Japan) -->
	<camera>
		<!-- Wikidata Item: Q93428008 -->
        <maker>Canon</maker>
        <model>Canon EOS Kiss X10i</model>
        <model lang="en">EOS Kiss X10i</model>
        <mount>Canon EF-S</mount>
        <cropfactor>1.613</cropfactor>
    </camera>


<!--
 /\ /\ /\ /\ /\ /\ /\ /\ /\ /\
       Canon EF-S mount
-->
	
<!--
        Canon RF mount
 \/ \/ \/ \/ \/ \/ \/ \/ \/ \/
-->

<!-- Device Name: Canon EOS R -->
	<camera>
		<!-- Wikidata Item: Q56479235 -->
        <maker>Canon</maker>
        <model>Canon EOS R</model>
        <model lang="en">EOS R</model>
        <mount>Canon RF</mount>
        <cropfactor>1</cropfactor>
    </camera>

<!-- Device Name: Canon EOS RP -->
	<camera>
		<!-- Wikidata Item: Q61729446 -->
        <maker>Canon</maker>
        <model>Canon EOS RP</model>
        <model lang="en">EOS RP</model>
        <mount>Canon RF</mount>
        <cropfactor>1</cropfactor>
    </camera>

<!-- Device Name: Canon EOS R3 -->
	<camera>
		<!-- Wikidata Item: Q106963109 -->
        <maker>Canon</maker>
        <model>Canon EOS R3</model>
        <model lang="en">EOS R3</model>
        <mount>Canon RF</mount>
        <cropfactor>1</cropfactor>
    </camera>

<!-- Device Name: Canon EOS R5 -->
	<camera>
		<!-- Wikidata Item: Q85750498 -->
        <maker>Canon</maker>
        <model>Canon EOS R5</model>
        <model lang="en">EOS R5</model>
        <mount>Canon RF</mount>
        <cropfactor>1</cropfactor>
    </camera>

<!-- Device Name: Canon EOS R6 -->
	<camera>
		<!-- Wikidata Item: Q97186199 -->
        <maker>Canon</maker>
        <model>Canon EOS R6</model>
        <model lang="en">EOS R6</model>
        <mount>Canon RF</mount>
        <cropfactor>1</cropfactor>
    </camera>

<!--
 /\ /\ /\ /\ /\ /\ /\ /\ /\ /\
        Canon RF mount
-->
	
</lensdatabase>
